MANIFEST.in
README.rst
requirements.txt
setup.py
xoskafka/VERSION
xoskafka/__init__.py
xoskafka/xoskafkaproducer.py
xoskafka.egg-info/PKG-INFO
xoskafka.egg-info/SOURCES.txt
xoskafka.egg-info/dependency_links.txt
xoskafka.egg-info/requires.txt
xoskafka.egg-info/top_level.txt