Metadata-Version: 1.1
Name: xoskafka
Version: 3.2.0
Summary: Wrapper around kafka for XOS
Home-page: UNKNOWN
Author: Zack Williams
Author-email: zdw@opennetworking.org
License: Apache v2
Platform: UNKNOWN
Classifier: License :: OSI Approved :: Apache Software License
